mbodied/__about__.py
mbodied/__init__.py
mbodied/agents/__init__.py
mbodied/agents/agent.py
mbodied/agents/cli.py
mbodied/agents/auto/__init__.py
mbodied/agents/auto/auto_agent.py
mbodied/agents/backends/__init__.py
mbodied/agents/backends/anthropic_backend.py
mbodied/agents/backends/backend.py
mbodied/agents/backends/gemini_backend.py
mbodied/agents/backends/gradio_backend.py
mbodied/agents/backends/httpx_backend.py
mbodied/agents/backends/ollama_backend.py
mbodied/agents/backends/openai_backend.py
mbodied/agents/backends/serializer.py
mbodied/agents/backends/vision2seq_backend.py
mbodied/agents/language/__init__.py
mbodied/agents/language/language_agent.py
mbodied/agents/language/rag_agent.py
mbodied/agents/language/utils.py
mbodied/agents/motion/__init__.py
mbodied/agents/motion/motor_agent.py
mbodied/agents/motion/openvla_agent.py
mbodied/agents/sense/README.md
mbodied/agents/sense/__init__.py
mbodied/agents/sense/depth_estimation_agent.py
mbodied/agents/sense/object_detection_agent.py
mbodied/agents/sense/segmentation_agent.py
mbodied/agents/sense/sensory_agent.py
mbodied/agents/sense/audio/__init__.py
mbodied/agents/sense/audio/audio_agent.py
mbodied/data/__init__.py
mbodied/data/recording.py
mbodied/data/replaying.py
mbodied/data/utils.py
mbodied/hardware/README.md
mbodied/hardware/__init__.py
mbodied/hardware/interface.py
mbodied/hardware/realsense_camera.py
mbodied/hardware/sim_interface.py
mbodied/robots/__init__.py
mbodied/robots/robot.py
mbodied/robots/robot_recording.py
mbodied/robots/sim_robot.py
mbodied/robots/xarm_robot.py
mbodied/types/__init__.py
mbodied/types/geometry.py
mbodied/types/message.py
mbodied/types/ndarray.py
mbodied/types/sample.py
mbodied/types/tool.py
mbodied/types/language/__init__.py
mbodied/types/language/control.py
mbodied/types/motion/__init__.py
mbodied/types/motion/control.py
mbodied/types/motion/motion.py
mbodied/types/sense/__init__.py
mbodied/types/sense/sensor_reading.py
mbodied/types/sense/vision.py
mbodied-1.5.1.dist-info/METADATA
mbodied-1.5.1.dist-info/WHEEL
mbodied-1.5.1.dist-info/entry_points.txt
mbodied-1.5.1.dist-info/licenses/LICENSE
mbodied-1.5.1.dist-info/RECORD
