Metadata-Version: 2.4
Name: mbodied
Version: 1.5.1
Summary: Embodied AI
Project-URL: Documentation, https://github.com/mbodiai/embodied-agents#readme
Project-URL: Issues, https://github.com/mbodiai/embodied-agents/issues
Project-URL: Source, https://github.com/mbodiai/embodied-agents
Author-email: Mbodi Team <info@mbodi.ai>
License-Expression: Apache-2.0
License-File: LICENSE
Classifier: Development Status :: 4 - Beta
Classifier: Programming Language :: Python
Classifier: Programming Language :: Python :: 3.10
Classifier: Programming Language :: Python :: 3.11
Classifier: Programming Language :: Python :: Implementation :: CPython
Classifier: Programming Language :: Python :: Implementation :: PyPy
Requires-Python: >=3.10
Requires-Dist: anthropic
Requires-Dist: art
Requires-Dist: backoff
Requires-Dist: chromadb
Requires-Dist: compress-pickle>=2.1.0
Requires-Dist: datasets
Requires-Dist: google-genai
Requires-Dist: gradio
Requires-Dist: gradio-client
Requires-Dist: gymnasium
Requires-Dist: h5py
Requires-Dist: jsonref
Requires-Dist: numpy>=1.26.4
Requires-Dist: openai
Requires-Dist: pillow
Requires-Dist: pydantic
Requires-Dist: rich-click>=1.8.3
Requires-Dist: ruamel-yaml>=0.18.6
Provides-Extra: all
Requires-Dist: open3d; extra == 'all'
Requires-Dist: openai-whisper; extra == 'all'
Requires-Dist: opencv-python; extra == 'all'
Requires-Dist: pyaudio; extra == 'all'
Requires-Dist: timm; extra == 'all'
Requires-Dist: torch; extra == 'all'
Requires-Dist: torchvision; extra == 'all'
Requires-Dist: transformers; extra == 'all'
Requires-Dist: wandb; extra == 'all'
Requires-Dist: xarm-python-sdk; extra == 'all'
Provides-Extra: audio
Requires-Dist: openai-whisper; extra == 'audio'
Requires-Dist: pyaudio; extra == 'audio'
Provides-Extra: extras
Requires-Dist: opencv-python; extra == 'extras'
Requires-Dist: torch; extra == 'extras'
Requires-Dist: transformers; extra == 'extras'
Requires-Dist: xarm-python-sdk; extra == 'extras'
